pepeline-1.2.2.dist-info/METADATA
pepeline-1.2.2.dist-info/WHEEL
pepeline-1.2.2.dist-info/licenses/LICENSE
pepeline/__init__.py
pepeline/__init__.pyi
pepeline/pepeline.abi3.so
pepeline/py.typed
pepeline-1.2.2.dist-info/RECORD
