Metadata-Version: 2.4
Name: pepeline
Version: 1.2.2
Classifier: Development Status :: 5 - Production/Stable
Classifier: Intended Audience :: Developers
Classifier: Intended Audience :: Science/Research
Classifier: License :: OSI Approved :: MIT License
Classifier: Operating System :: MacOS
Classifier: Operating System :: Microsoft :: Windows
Classifier: Operating System :: POSIX
Classifier: Operating System :: Unix
Classifier: Programming Language :: Python :: 3
Classifier: Programming Language :: Python :: 3 :: Only
Classifier: Programming Language :: Python :: 3.10
Classifier: Programming Language :: Python :: 3.11
Classifier: Programming Language :: Python :: 3.12
Classifier: Programming Language :: Python :: 3.13
Classifier: Programming Language :: Python :: Implementation :: CPython
Classifier: Programming Language :: Rust
Classifier: Topic :: Scientific/Engineering :: Image Processing
Classifier: Typing :: Typed
Requires-Dist: numpy>=2
License-File: LICENSE
Summary: A high-speed framework for image processing.
Requires-Python: >=3.10
Project-URL: homepage, https://github.com/rewaifu/pepecore/tree/main/pepecore-py-bindings
Project-URL: repository, https://github.com/rewaifu/pepecore/tree/main/pepecore-py-bindings
Project-URL: documentation, https://github.com/rewaifu/pepecore/tree/main/pepecore-py-bindings#readme
